odoo/addons/resource_leaves_geographic/README.rst
odoo/addons/resource_leaves_geographic/__init__.py
odoo/addons/resource_leaves_geographic/__manifest__.py
odoo/addons/resource_leaves_geographic/i18n/es.po
odoo/addons/resource_leaves_geographic/i18n/it.po
odoo/addons/resource_leaves_geographic/i18n/resource_leaves_geographic.pot
odoo/addons/resource_leaves_geographic/models/__init__.py
odoo/addons/resource_leaves_geographic/models/hr_employee.py
odoo/addons/resource_leaves_geographic/models/resource_calendar.py
odoo/addons/resource_leaves_geographic/models/resource_calendar_leaves.py
odoo/addons/resource_leaves_geographic/readme/CONTEXT.md
odoo/addons/resource_leaves_geographic/readme/CONTRIBUTORS.md
odoo/addons/resource_leaves_geographic/readme/DESCRIPTION.md
odoo/addons/resource_leaves_geographic/readme/USAGE.md
odoo/addons/resource_leaves_geographic/static/description/icon.png
odoo/addons/resource_leaves_geographic/static/description/index.html
odoo/addons/resource_leaves_geographic/tests/__init__.py
odoo/addons/resource_leaves_geographic/tests/test_resource_calendar_leaves.py
odoo/addons/resource_leaves_geographic/views/resource_calendar_leaves_views.xml
odoo_addon_resource_leaves_geographic-16.0.1.0.1.dist-info/METADATA
odoo_addon_resource_leaves_geographic-16.0.1.0.1.dist-info/WHEEL
odoo_addon_resource_leaves_geographic-16.0.1.0.1.dist-info/top_level.txt
odoo_addon_resource_leaves_geographic-16.0.1.0.1.dist-info/RECORD
