Metadata-Version: 2.1
Name: odoo-addon-resource_leaves_geographic
Version: 16.0.1.0.1
Summary: Add geographic State to Resource Calendar Leaves
Home-page: https://github.com/OCA/hr-holidays
Author: Moduon, Odoo Community Association (OCA)
Author-email: support@odoo-community.org
License: LGPL-3
Classifier: Programming Language :: Python
Classifier: Framework :: Odoo
Classifier: Framework :: Odoo :: 16.0
Classifier: License :: OSI Approved :: GNU Lesser General Public License v3 (LGPLv3)
Classifier: Development Status :: 3 - Alpha
Requires-Python: >=3.10
Requires-Dist: odoo <16.1dev,>=16.0a
